interrupt_handler/__init__.py
interrupt_handler/default_callback.py
interrupt_handler/interrupt_handler.py
InterruptHandler-0.0.4.dist-info/LICENSE
InterruptHandler-0.0.4.dist-info/METADATA
InterruptHandler-0.0.4.dist-info/WHEEL
InterruptHandler-0.0.4.dist-info/top_level.txt
InterruptHandler-0.0.4.dist-info/RECORD
